textcurator_llm_py/__init__.py
textcurator_llm_py/main.py
textcurator_llm_py/prompts.py
textcurator_llm_py-2025.12.21161315.dist-info/METADATA
textcurator_llm_py-2025.12.21161315.dist-info/WHEEL
textcurator_llm_py-2025.12.21161315.dist-info/top_level.txt
textcurator_llm_py-2025.12.21161315.dist-info/RECORD
