Metadata-Version: 2.4
Name: textcurator-llm-py
Version: 2025.12.21161315
Summary: A new package would process user-provided text inputs, such as headlines or short descriptions, and generate structured summaries or categorizations using an LLM. It would be particularly useful for c
Author-email: textcurator-llm-py <hi@eugene.plus>
License: MIT
Project-URL: Homepage, https://github.com/chigwell/textcurator-llm-py
Requires-Python: >=3.9
Requires-Dist: langchain-llm7>=0.0.0
Requires-Dist: llmatch-messages>=0.0.0
Requires-Dist: langchain-core>=0.3.0
